Compiled from "Issue_45.kt"
final class testData.Issue_45Kt$main$1 extends kotlin.jvm.internal.Lambda implements kotlin.jvm.functions.Function0<kotlin.Unit> {
  public static final testData.Issue_45Kt$main$1 INSTANCE;

  testData.Issue_45Kt$main$1();
    Code:
       0: aload_0
       1: iconst_0
       2: invokespecial #12                 // Method kotlin/jvm/internal/Lambda."<init>":(I)V
       5: return
    LocalVariableTable:
      Start  Length  Slot  Name   Signature
          0       6     0  this   LtestData/Issue_45Kt$main$1;

  public final void invoke();
    Code:
       0: invokestatic  #20                 // Method testData/Issue_45Kt.f2:()V
       3: return
    LineNumberTable:
      line 5: 0
      line 6: 3
    LocalVariableTable:
      Start  Length  Slot  Name   Signature
          0       4     0  this   LtestData/Issue_45Kt$main$1;

  public java.lang.Object invoke();
    Code:
       0: aload_0
       1: invokevirtual #23                 // Method invoke:()V
       4: getstatic     #29                 // Field kotlin/Unit.INSTANCE:Lkotlin/Unit;
       7: areturn
    LineNumberTable:
      line 4: 0
    LocalVariableTable:
      Start  Length  Slot  Name   Signature
          0       8     0  this   LtestData/Issue_45Kt$main$1;

  static {};
    Code:
       0: new           #2                  // class testData/Issue_45Kt$main$1
       3: dup
       4: invokespecial #32                 // Method "<init>":()V
       7: putstatic     #34                 // Field INSTANCE:LtestData/Issue_45Kt$main$1;
      10: return
}
Compiled from "Issue_45.kt"
public final class testData.Issue_45Kt {
  public static final void main();
    Code:
       0: getstatic     #12                 // Field testData/Issue_45Kt$main$1.INSTANCE:LtestData/Issue_45Kt$main$1;
       3: checkcast     #14                 // class kotlin/jvm/functions/Function0
       6: invokestatic  #18                 // Method f1:(Lkotlin/jvm/functions/Function0;)V
       9: return
    LineNumberTable:
      line 4: 0
      line 7: 9

  public static final void f1(kotlin.jvm.functions.Function0<kotlin.Unit>);
    Code:
       0: aload_0
       1: invokeinterface #24,  1           // InterfaceMethod kotlin/jvm/functions/Function0.invoke:()Ljava/lang/Object;
       6: pop
       7: return
    LineNumberTable:
      line 9: 0
    LocalVariableTable:
      Start  Length  Slot  Name   Signature
          0       8     0     f   Lkotlin/jvm/functions/Function0;

  public static final void f2();
    Code:
       0: ldc           #29                 // String Hi
       2: getstatic     #35                 // Field java/lang/System.out:Ljava/io/PrintStream;
       5: swap
       6: invokevirtual #41                 // Method java/io/PrintStream.println:(Ljava/lang/Object;)V
       9: return
    LineNumberTable:
      line 11: 0
      line 12: 9

  public static void main(java.lang.String[]);
    Code:
       0: invokestatic  #44                 // Method main:()V
       3: return
    LocalVariableTable:
      Start  Length  Slot  Name   Signature
          0       4     0  args   [Ljava/lang/String;
}